kpireport_scp/__init__.py
kpireport_scp/output.py
kpireport_scp-0.0.3.dist-info/METADATA
kpireport_scp-0.0.3.dist-info/WHEEL
kpireport_scp-0.0.3.dist-info/entry_points.txt
kpireport_scp-0.0.3.dist-info/top_level.txt
kpireport_scp-0.0.3.dist-info/RECORD
