Metadata-Version: 2.1
Name: kpireport-scp
Version: 0.0.3
Summary: An SCP output driver for kpireporter
Home-page: https://kpireporter.com
Author: KPI Reporter LLC
Author-email: dev@kpireporter.com
License: Prosperity Public License
Platform: UNKNOWN
Requires-Dist: kpireport
Requires-Dist: kpireport-static
Requires-Dist: fabric
